CHANGELOG.rst
LICENSE
MANIFEST.in
README.rst
setup.py
forwardable/__init__.py
forwardable.egg-info/PKG-INFO
forwardable.egg-info/SOURCES.txt
forwardable.egg-info/dependency_links.txt
forwardable.egg-info/top_level.txt
forwardable/test/__init__.py
forwardable/test/test_def_delegator.py
forwardable/test/test_def_delegators.py
forwardable/test/test_forwardable.py