Metadata-Version: 1.1
Name: forwardable
Version: 0.4.0
Summary: Forwardable as in Ruby's stdlib
Home-page: https://github.com/5long/forwardable
Author: Whyme Lyu
Author-email: callme5long@gmail.com
License: MIT
Platform: UNKNOWN
Classifier: Development Status :: 3 - Alpha
Classifier: Intended Audience :: Developers
Classifier: License :: OSI Approved :: MIT License
Classifier: Topic :: Software Development :: Code Generators
Classifier: Programming Language :: Python
Classifier: Programming Language :: Python :: 2.7
Classifier: Programming Language :: Python :: 3.3
